{
  "FileName": null,
  "RepoPath": "models\\mg\\marvel_r\\marvel_r_electric_performance\\screens_3.jpg",
  "CloudPath": "models/mg/marvel_r/marvel_r_electric_performance/screens_3.jpg",
  "ExternalUrl": "https://media.evkx.net/multimedia/models/mg/marvel_r/marvel_r_electric_performance/screens_3.jpg",
  "Width": 3000,
  "Height": 1991,
  "HasXSmallThumb": true,
  "HasSmallThumb": true,
  "HasMediumThumb": true,
  "Hash": "2thnvVOx5sPeweCCZX1PNQ==",
  "Tags": null,
  "Size": 525284,
  "Description": null
}