{
  "FileName": null,
  "RepoPath": "technology\\charging\\ontheroadcharging\\teslasupercharger_1.jpg",
  "CloudPath": "technology/charging/ontheroadcharging/teslasupercharger_1.jpg",
  "ExternalUrl": "https://media.evkx.net/multimedia/technology/charging/ontheroadcharging/teslasupercharger_1.jpg",
  "Width": 3000,
  "Height": 1948,
  "HasXSmallThumb": true,
  "HasSmallThumb": true,
  "HasMediumThumb": true,
  "Hash": "Gjnja3Tt6NCo/Oh8D8zoqw==",
  "Tags": null,
  "Size": 2094580,
  "Description": null
}