{
  "FileName": null,
  "RepoPath": "models\\dongfeng\\nammi_box\\nammi_box_42.3kwh\\headlights_1.jpg",
  "CloudPath": "models/dongfeng/nammi_box/nammi_box_42.3kwh/headlights_1.jpg",
  "ExternalUrl": "https://media.evkx.net/multimedia/models/dongfeng/nammi_box/nammi_box_42.3kwh/headlights_1.jpg",
  "Width": 1920,
  "Height": 1080,
  "HasXSmallThumb": true,
  "HasSmallThumb": true,
  "HasMediumThumb": true,
  "Hash": "koYRhs6815D5XVKqpYpc9A==",
  "Tags": null,
  "Size": 197917,
  "Description": null
}