{
  "FileName": null,
  "RepoPath": "models\\gmc\\sierra_ev\\sierra_ev_denali_edition_1\\exterior_1.jpg",
  "CloudPath": "models/gmc/sierra_ev/sierra_ev_denali_edition_1/exterior_1.jpg",
  "ExternalUrl": "https://media.evkx.net/multimedia/models/gmc/sierra_ev/sierra_ev_denali_edition_1/exterior_1.jpg",
  "Width": 1920,
  "Height": 1080,
  "HasXSmallThumb": true,
  "HasSmallThumb": true,
  "HasMediumThumb": true,
  "Hash": "IqwUe2vn5gdKmB960a9MYw==",
  "Tags": null,
  "Size": 422402,
  "Description": null
}