{
  "FileName": "secondrowseats_3.jpg",
  "RepoPath": "models\\maserati\\granturismo\\granturismo_folgore\\secondrowseats_3.jpg",
  "CloudPath": "models/maserati/granturismo/granturismo_folgore/secondrowseats_3.jpg",
  "ExternalUrl": "https://media.evkx.net/multimedia/models/maserati/granturismo/granturismo_folgore/secondrowseats_3.jpg",
  "Width": 3000,
  "Height": 2000,
  "HasXSmallThumb": true,
  "HasSmallThumb": true,
  "HasMediumThumb": true,
  "Hash": "//cW2pZkazsPJGTwTkDQdA==",
  "Tags": null,
  "Size": 3673532,
  "Description": null
}